[   
            {
                "label": "Prénom",
                "property": "given_name",
                "display": true
            },
            {
                "label": "Nom de famille",
                "property": "family_name",
                "display": true
            },
            {
                "label": "Pays",
                "property": "app_metadata.country",
                "display": true,
                "create": {
                    "required": true,
                    "display": true,
                    "type": "select",
                    "component": "InputCombo",
                    "options": [ { "value": "AF", "label": "Afghanistan" }, { "value": "ZA", "label": "Afrique du Sud" }, { "value": "AL", "label": "Albanie" }, { "value": "DZ", "label": "Algérie" }, { "value": "DE", "label": "Allemagne" }, { "value": "AD", "label": "Andorre" }, { "value": "AO", "label": "Angola" }, { "value": "AG", "label": "Antigua-et-Barbuda" }, { "value": "SA", "label": "Arabie Saoudite" }, { "value": "AR", "label": "Argentine" }, { "value": "AM", "label": "Arménie" }, { "value": "AU", "label": "Australie" }, { "value": "AT", "label": "Autriche" }, { "value": "AZ", "label": "Azerbaïdjan" }, { "value": "BS", "label": "Bahamas" }, { "value": "BH", "label": "Bahreïn" }, { "value": "BD", "label": "Bangladesh" }, { "value": "BB", "label": "Barbade" }, { "value": "BE", "label": "Belgique" }, { "value": "BZ", "label": "Belize" }, { "value": "BJ", "label": "Bénin" }, { "value": "BT", "label": "Bhoutan" }, { "value": "BY", "label": "Biélorussie" }, { "value": "MM", "label": "Birmanie" }, { "value": "BO", "label": "Bolivie" }, { "value": "BA", "label": "Bosnie-Herzégovine" }, { "value": "BW", "label": "Botswana" }, { "value": "BR", "label": "Brésil" }, { "value": "BN", "label": "Brunei" }, { "value": "BG", "label": "Bulgarie" }, { "value": "BF", "label": "Burkina Faso" }, { "value": "BI", "label": "Burundi" }, { "value": "KH", "label": "Cambodge" }, { "value": "CM", "label": "Cameroun" }, { "value": "CA", "label": "Canada" }, { "value": "CV", "label": "Cap-Vert" }, { "value": "CL", "label": "Chili" }, { "value": "CN", "label": "Chine" }, { "value": "CY", "label": "Chypre" }, { "value": "CO", "label": "Colombie" }, { "value": "KM", "label": "Comores" }, { "value": "CG", "label": "Congo-Brazzaville" }, { "value": "CD", "label": "Congo-Kinshasa" }, { "value": "KP", "label": "Corée du Nord" }, { "value": "KR", "label": "Corée du Sud" }, { "value": "CR", "label": "Costa Rica" }, { "value": "CI", "label": "Côte d'Ivoire" }, { "value": "HR", "label": "Croatie" }, { "value": "CU", "label": "Cuba" }, { "value": "DK", "label": "Danemark" }, { "value": "DJ", "label": "Djibouti" }, { "value": "DM", "label": "Dominique" }, { "value": "EG", "label": "Égypte" }, { "value": "AE", "label": "Émirats Arabes Unis" }, { "value": "EC", "label": "Équateur" }, { "value": "ER", "label": "Érythrée" }, { "value": "ES", "label": "Espagne" }, { "value": "EE", "label": "Estonie" }, { "value": "SZ", "label": "Eswatini" }, { "value": "US", "label": "États-Unis" }, { "value": "ET", "label": "Éthiopie" }, { "value": "FJ", "label": "Fidji" }, { "value": "FI", "label": "Finlande" }, { "value": "FR", "label": "France" }, { "value": "GA", "label": "Gabon" }, { "value": "GM", "label": "Gambie" }, { "value": "GE", "label": "Géorgie" }, { "value": "GH", "label": "Ghana" }, { "value": "GR", "label": "Grèce" }, { "value": "GD", "label": "Grenade" }, { "value": "GT", "label": "Guatemala" }, { "value": "GN", "label": "Guinée" }, { "value": "GW", "label": "Guinée-Bissau" }, { "value": "GQ", "label": "Guinée Équatoriale" }, { "value": "GY", "label": "Guyana" }, { "value": "HT", "label": "Haïti" }, { "value": "HN", "label": "Honduras" }, { "value": "HU", "label": "Hongrie" }, { "value": "MH", "label": "Îles Marshall" }, { "value": "SB", "label": "Îles Salomon" }, { "value": "IN", "label": "Inde" }, { "value": "ID", "label": "Indonésie" }, { "value": "IQ", "label": "Irak" }, { "value": "IR", "label": "Iran" }, { "value": "IE", "label": "Irlande" }, { "value": "IS", "label": "Islande" }, { "value": "IL", "label": "Israël" }, { "value": "IT", "label": "Italie" }, { "value": "JM", "label": "Jamaïque" }, { "value": "JP", "label": "Japon" }, { "value": "JO", "label": "Jordanie" }, { "value": "KZ", "label": "Kazakhstan" }, { "value": "KE", "label": "Kenya" }, { "value": "KG", "label": "Kirghizistan" }, { "value": "KI", "label": "Kiribati" }, { "value": "XK", "label": "Kosovo" }, { "value": "KW", "label": "Koweït" }, { "value": "LA", "label": "Laos" }, { "value": "LS", "label": "Lesotho" }, { "value": "LV", "label": "Lettonie" }, { "value": "LB", "label": "Liban" }, { "value": "LR", "label": "Libéria" }, { "value": "LY", "label": "Libye" }, { "value": "LI", "label": "Liechtenstein" }, { "value": "LT", "label": "Lituanie" }, { "value": "LU", "label": "Luxembourg" }, { "value": "MK", "label": "Macédoine du Nord" }, { "value": "MG", "label": "Madagascar" }, { "value": "MY", "label": "Malaisie" }, { "value": "MW", "label": "Malawi" }, { "value": "MV", "label": "Maldives" }, { "value": "ML", "label": "Mali" }, { "value": "MT", "label": "Malte" }, { "value": "MA", "label": "Maroc" }, { "value": "MU", "label": "Maurice" }, { "value": "MR", "label": "Mauritanie" }, { "value": "MX", "label": "Mexique" }, { "value": "FM", "label": "Micronésie" }, { "value": "MD", "label": "Moldavie" }, { "value": "MC", "label": "Monaco" }, { "value": "MN", "label": "Mongolie" }, { "value": "ME", "label": "Monténégro" }, { "value": "MZ", "label": "Mozambique" }, { "value": "NA", "label": "Namibie" }, { "value": "NR", "label": "Nauru" }, { "value": "NP", "label": "Népal" }, { "value": "NI", "label": "Nicaragua" }, { "value": "NE", "label": "Niger" }, { "value": "NG", "label": "Nigeria" }, { "value": "NO", "label": "Norvège" }, { "value": "NZ", "label": "Nouvelle-Zélande" }, { "value": "OM", "label": "Oman" }, { "value": "UG", "label": "Ouganda" }, { "value": "UZ", "label": "Ouzbékistan" }, { "value": "PK", "label": "Pakistan" }, { "value": "PW", "label": "Palaos" }, { "value": "PA", "label": "Panama" }, { "value": "PG", "label": "Papouasie-Nouvelle-Guinée" }, { "value": "PY", "label": "Paraguay" }, { "value": "NL", "label": "Pays-Bas" }, { "value": "PE", "label": "Pérou" }, { "value": "PH", "label": "Philippines" }, { "value": "PL", "label": "Pologne" }, { "value": "PT", "label": "Portugal" }, { "value": "QA", "label": "Qatar" }, { "value": "CF", "label": "République Centrafricaine" }, { "value": "DO", "label": "République Dominicaine" }, { "value": "CZ", "label": "République Tchèque" }, { "value": "RO", "label": "Roumanie" }, { "value": "GB", "label": "Royaume-Uni" }, { "value": "RU", "label": "Russie" }, { "value": "RW", "label": "Rwanda" }, { "value": "KN", "label": "Saint-Kitts-et-Nevis" }, { "value": "VC", "label": "Saint-Vincent-et-les-Grenadines" }, { "value": "LC", "label": "Sainte-Lucie" }, { "value": "SM", "label": "Saint-Marin" }, { "value": "SV", "label": "Salvador" }, { "value": "WS", "label": "Samoa" }, { "value": "ST", "label": "São Tomé-et-Príncipe" }, { "value": "SN", "label": "Sénégal" }, { "value": "RS", "label": "Serbie" }, { "value": "SC", "label": "Seychelles" }, { "value": "SL", "label": "Sierra Leone" }, { "value": "SG", "label": "Singapour" }, { "value": "SK", "label": "Slovaquie" }, { "value": "SI", "label": "Slovénie" }, { "value": "SO", "label": "Somalie" }, { "value": "SD", "label": "Soudan" }, { "value": "SS", "label": "Soudan du Sud" }, { "value": "LK", "label": "Sri Lanka" }, { "value": "SE", "label": "Suède" }, { "value": "CH", "label": "Suisse" }, { "value": "SR", "label": "Suriname" }, { "value": "SY", "label": "Syrie" }, { "value": "TJ", "label": "Tadjikistan" }, { "value": "TZ", "label": "Tanzanie" }, { "value": "TD", "label": "Tchad" }, { "value": "TH", "label": "Thaïlande" }, { "value": "TL", "label": "Timor Oriental" }, { "value": "TG", "label": "Togo" }, { "value": "TO", "label": "Tonga" }, { "value": "TT", "label": "Trinité-et-Tobago" }, { "value": "TN", "label": "Tunisie" }, { "value": "TM", "label": "Turkménistan" }, { "value": "TR", "label": "Turquie" }, { "value": "TV", "label": "Tuvalu" }, { "value": "UA", "label": "Ukraine" }, { "value": "UY", "label": "Uruguay" }, { "value": "VU", "label": "Vanuatu" }, { "value": "VA", "label": "Vatican" }, { "value": "VE", "label": "Venezuela" }, { "value": "VN", "label": "Viêt Nam" }, { "value": "YE", "label": "Yémen" }, { "value": "ZM", "label": "Zambie" }, { "value": "ZW", "label": "Zimbabwe" }]
                  },
                  "edit": {
                    "required": true,
                    "display": true,
                    "type": "select",
                    "component": "InputCombo",
                    "options": [ { "value": "AF", "label": "Afghanistan" }, { "value": "ZA", "label": "Afrique du Sud" }, { "value": "AL", "label": "Albanie" }, { "value": "DZ", "label": "Algérie" }, { "value": "DE", "label": "Allemagne" }, { "value": "AD", "label": "Andorre" }, { "value": "AO", "label": "Angola" }, { "value": "AG", "label": "Antigua-et-Barbuda" }, { "value": "SA", "label": "Arabie Saoudite" }, { "value": "AR", "label": "Argentine" }, { "value": "AM", "label": "Arménie" }, { "value": "AU", "label": "Australie" }, { "value": "AT", "label": "Autriche" }, { "value": "AZ", "label": "Azerbaïdjan" }, { "value": "BS", "label": "Bahamas" }, { "value": "BH", "label": "Bahreïn" }, { "value": "BD", "label": "Bangladesh" }, { "value": "BB", "label": "Barbade" }, { "value": "BE", "label": "Belgique" }, { "value": "BZ", "label": "Belize" }, { "value": "BJ", "label": "Bénin" }, { "value": "BT", "label": "Bhoutan" }, { "value": "BY", "label": "Biélorussie" }, { "value": "MM", "label": "Birmanie" }, { "value": "BO", "label": "Bolivie" }, { "value": "BA", "label": "Bosnie-Herzégovine" }, { "value": "BW", "label": "Botswana" }, { "value": "BR", "label": "Brésil" }, { "value": "BN", "label": "Brunei" }, { "value": "BG", "label": "Bulgarie" }, { "value": "BF", "label": "Burkina Faso" }, { "value": "BI", "label": "Burundi" }, { "value": "KH", "label": "Cambodge" }, { "value": "CM", "label": "Cameroun" }, { "value": "CA", "label": "Canada" }, { "value": "CV", "label": "Cap-Vert" }, { "value": "CL", "label": "Chili" }, { "value": "CN", "label": "Chine" }, { "value": "CY", "label": "Chypre" }, { "value": "CO", "label": "Colombie" }, { "value": "KM", "label": "Comores" }, { "value": "CG", "label": "Congo-Brazzaville" }, { "value": "CD", "label": "Congo-Kinshasa" }, { "value": "KP", "label": "Corée du Nord" }, { "value": "KR", "label": "Corée du Sud" }, { "value": "CR", "label": "Costa Rica" }, { "value": "CI", "label": "Côte d'Ivoire" }, { "value": "HR", "label": "Croatie" }, { "value": "CU", "label": "Cuba" }, { "value": "DK", "label": "Danemark" }, { "value": "DJ", "label": "Djibouti" }, { "value": "DM", "label": "Dominique" }, { "value": "EG", "label": "Égypte" }, { "value": "AE", "label": "Émirats Arabes Unis" }, { "value": "EC", "label": "Équateur" }, { "value": "ER", "label": "Érythrée" }, { "value": "ES", "label": "Espagne" }, { "value": "EE", "label": "Estonie" }, { "value": "SZ", "label": "Eswatini" }, { "value": "US", "label": "États-Unis" }, { "value": "ET", "label": "Éthiopie" }, { "value": "FJ", "label": "Fidji" }, { "value": "FI", "label": "Finlande" }, { "value": "FR", "label": "France" }, { "value": "GA", "label": "Gabon" }, { "value": "GM", "label": "Gambie" }, { "value": "GE", "label": "Géorgie" }, { "value": "GH", "label": "Ghana" }, { "value": "GR", "label": "Grèce" }, { "value": "GD", "label": "Grenade" }, { "value": "GT", "label": "Guatemala" }, { "value": "GN", "label": "Guinée" }, { "value": "GW", "label": "Guinée-Bissau" }, { "value": "GQ", "label": "Guinée Équatoriale" }, { "value": "GY", "label": "Guyana" }, { "value": "HT", "label": "Haïti" }, { "value": "HN", "label": "Honduras" }, { "value": "HU", "label": "Hongrie" }, { "value": "MH", "label": "Îles Marshall" }, { "value": "SB", "label": "Îles Salomon" }, { "value": "IN", "label": "Inde" }, { "value": "ID", "label": "Indonésie" }, { "value": "IQ", "label": "Irak" }, { "value": "IR", "label": "Iran" }, { "value": "IE", "label": "Irlande" }, { "value": "IS", "label": "Islande" }, { "value": "IL", "label": "Israël" }, { "value": "IT", "label": "Italie" }, { "value": "JM", "label": "Jamaïque" }, { "value": "JP", "label": "Japon" }, { "value": "JO", "label": "Jordanie" }, { "value": "KZ", "label": "Kazakhstan" }, { "value": "KE", "label": "Kenya" }, { "value": "KG", "label": "Kirghizistan" }, { "value": "KI", "label": "Kiribati" }, { "value": "XK", "label": "Kosovo" }, { "value": "KW", "label": "Koweït" }, { "value": "LA", "label": "Laos" }, { "value": "LS", "label": "Lesotho" }, { "value": "LV", "label": "Lettonie" }, { "value": "LB", "label": "Liban" }, { "value": "LR", "label": "Libéria" }, { "value": "LY", "label": "Libye" }, { "value": "LI", "label": "Liechtenstein" }, { "value": "LT", "label": "Lituanie" }, { "value": "LU", "label": "Luxembourg" }, { "value": "MK", "label": "Macédoine du Nord" }, { "value": "MG", "label": "Madagascar" }, { "value": "MY", "label": "Malaisie" }, { "value": "MW", "label": "Malawi" }, { "value": "MV", "label": "Maldives" }, { "value": "ML", "label": "Mali" }, { "value": "MT", "label": "Malte" }, { "value": "MA", "label": "Maroc" }, { "value": "MU", "label": "Maurice" }, { "value": "MR", "label": "Mauritanie" }, { "value": "MX", "label": "Mexique" }, { "value": "FM", "label": "Micronésie" }, { "value": "MD", "label": "Moldavie" }, { "value": "MC", "label": "Monaco" }, { "value": "MN", "label": "Mongolie" }, { "value": "ME", "label": "Monténégro" }, { "value": "MZ", "label": "Mozambique" }, { "value": "NA", "label": "Namibie" }, { "value": "NR", "label": "Nauru" }, { "value": "NP", "label": "Népal" }, { "value": "NI", "label": "Nicaragua" }, { "value": "NE", "label": "Niger" }, { "value": "NG", "label": "Nigeria" }, { "value": "NO", "label": "Norvège" }, { "value": "NZ", "label": "Nouvelle-Zélande" }, { "value": "OM", "label": "Oman" }, { "value": "UG", "label": "Ouganda" }, { "value": "UZ", "label": "Ouzbékistan" }, { "value": "PK", "label": "Pakistan" }, { "value": "PW", "label": "Palaos" }, { "value": "PA", "label": "Panama" }, { "value": "PG", "label": "Papouasie-Nouvelle-Guinée" }, { "value": "PY", "label": "Paraguay" }, { "value": "NL", "label": "Pays-Bas" }, { "value": "PE", "label": "Pérou" }, { "value": "PH", "label": "Philippines" }, { "value": "PL", "label": "Pologne" }, { "value": "PT", "label": "Portugal" }, { "value": "QA", "label": "Qatar" }, { "value": "CF", "label": "République Centrafricaine" }, { "value": "DO", "label": "République Dominicaine" }, { "value": "CZ", "label": "République Tchèque" }, { "value": "RO", "label": "Roumanie" }, { "value": "GB", "label": "Royaume-Uni" }, { "value": "RU", "label": "Russie" }, { "value": "RW", "label": "Rwanda" }, { "value": "KN", "label": "Saint-Kitts-et-Nevis" }, { "value": "VC", "label": "Saint-Vincent-et-les-Grenadines" }, { "value": "LC", "label": "Sainte-Lucie" }, { "value": "SM", "label": "Saint-Marin" }, { "value": "SV", "label": "Salvador" }, { "value": "WS", "label": "Samoa" }, { "value": "ST", "label": "São Tomé-et-Príncipe" }, { "value": "SN", "label": "Sénégal" }, { "value": "RS", "label": "Serbie" }, { "value": "SC", "label": "Seychelles" }, { "value": "SL", "label": "Sierra Leone" }, { "value": "SG", "label": "Singapour" }, { "value": "SK", "label": "Slovaquie" }, { "value": "SI", "label": "Slovénie" }, { "value": "SO", "label": "Somalie" }, { "value": "SD", "label": "Soudan" }, { "value": "SS", "label": "Soudan du Sud" }, { "value": "LK", "label": "Sri Lanka" }, { "value": "SE", "label": "Suède" }, { "value": "CH", "label": "Suisse" }, { "value": "SR", "label": "Suriname" }, { "value": "SY", "label": "Syrie" }, { "value": "TJ", "label": "Tadjikistan" }, { "value": "TZ", "label": "Tanzanie" }, { "value": "TD", "label": "Tchad" }, { "value": "TH", "label": "Thaïlande" }, { "value": "TL", "label": "Timor Oriental" }, { "value": "TG", "label": "Togo" }, { "value": "TO", "label": "Tonga" }, { "value": "TT", "label": "Trinité-et-Tobago" }, { "value": "TN", "label": "Tunisie" }, { "value": "TM", "label": "Turkménistan" }, { "value": "TR", "label": "Turquie" }, { "value": "TV", "label": "Tuvalu" }, { "value": "UA", "label": "Ukraine" }, { "value": "UY", "label": "Uruguay" }, { "value": "VU", "label": "Vanuatu" }, { "value": "VA", "label": "Vatican" }, { "value": "VE", "label": "Venezuela" }, { "value": "VN", "label": "Viêt Nam" }, { "value": "YE", "label": "Yémen" }, { "value": "ZM", "label": "Zambie" }, { "value": "ZW", "label": "Zimbabwe" }]
                  }
            },
            {
                "label": "Civilité",
                "property": "app_metadata.civility",
                "display": true
            },
            {
                "label": "Bloqué",
                "property": "isBlocked",
                "display": true
            },
            {
                "label": "Bloqué par brute force",
                "property": "blocked_for",
                "display": true
            },
            {
                "label": "Dernière connexion",
                "property": "last_login",
                "display": true
            },
            {
                "label": "Nombre de connexions",
                "property": "logins_count",
                "display": true
            },
            {
                "label": "MFA",
                "property": "multifactor",
                "display": true
            },
            {
                "label": "Date de création",
                "property": "created_at",
                "display": true
            },
            {
                "label": "Dernière mise à jour",
                "property": "updated_at",
                "display": true
            },
            {
                "label": "ID utilisateur Auth0",
                "property": "user_id",
                "display": true
            },
            {
                "label": "Email vérifié",
                "property": "email_verified",
                "display": true
            },
            {
                "label": "Dernière modification du mot de passe",
                "property": "last_password_reset",
                "display": true
            },
            {
                "label": "Dernière modification du MFA",
                "property": "multifactor_last_modified",
                "display": true
            },
            {
                "label": "Surnom",
                "property": "nickname",
                "display": false
            },
            {
                "label": "Bloqué pour",
                "property": "blocked_for",
                "display": false
            },
            {
                "label": "Nom",
                "property": "name",
                "display": true
            },
            {
                "label": "Dernière IP",
                "property": "last_ip",
                "display": false
            },
            {
                "label": "Mot de passe",
                "property": "password",
                "display": false,
                "create" : {
                   "display" : false,
                   "type" : "hidden",
                   "disabled": true
                }
            },
            {
                "label": "Confirmer le mot de passe",
                "property": "repeatPassword",
                "display": false,
                "create" : {
                   "display" : false,
                   "type" : "hidden",
                   "disabled": true
                }
            },
            {
                "label": "Connection",
                "property": "identity",
                "display": false
            }
          ]